cve_checker/__init__.py
cve_checker/cli.py
cve_checker/cve_checker.py
cve_checker/cve_data_fetcher.py
cve_checker/dependency_scanner.py
cve_checker/report_generator.py
cve_checker/risk_scorer.py
cve_checker/vulnerability_checker.py
cve_checker-0.1.1.dist-info/LICENSE
cve_checker-0.1.1.dist-info/METADATA
cve_checker-0.1.1.dist-info/WHEEL
cve_checker-0.1.1.dist-info/entry_points.txt
cve_checker-0.1.1.dist-info/top_level.txt
cve_checker-0.1.1.dist-info/RECORD
