Metadata-Version: 2.1
Name: cve_checker
Version: 0.1.1
Summary: A library for checking CVE vulnerabilities in software dependencies
Home-page: https://github.com/bassemAbidi/cve_checker
Author: Bassem Abidi
Author-email: abidi.bassem@me.com
Classifier: Development Status :: 3 - Alpha
Classifier: Intended Audience :: Developers
Classifier: License :: OSI Approved :: MIT License
Classifier: Operating System :: OS Independent
Classifier: Programming Language :: Python :: 3
Classifier: Programming Language :: Python :: 3.7
Classifier: Programming Language :: Python :: 3.8
Classifier: Programming Language :: Python :: 3.9
Classifier: Programming Language :: Python :: 3.10
Requires-Python: >=3.7
License-File: LICENSE
Requires-Dist: aiohttp
Requires-Dist: pyyaml
Requires-Dist: toml
